raft/__init__.py
raft/cluster.py
raft/main.py
raft/node.py
raft/states/__init__.py
raft/states/candidate.py
raft/states/follower.py
raft/states/idle.py
raft/states/leader.py
raft/states/state.py
raft/utils/__init__.py
raft/utils/database.py
raft/utils/machine.py
raft/utils/models.py
raft/utils/timer.py
raft_cluster-0.1.0.dist-info/LICENSE
raft_cluster-0.1.0.dist-info/METADATA
raft_cluster-0.1.0.dist-info/WHEEL
raft_cluster-0.1.0.dist-info/entry_points.txt
raft_cluster-0.1.0.dist-info/top_level.txt
raft_cluster-0.1.0.dist-info/RECORD
