Metadata-Version: 2.1
Name: raft-cluster
Version: 0.1.0
Summary: A Raft library.
Home-page: https://github.com/Muti-Kara/Raft
Author: Muti-Kara
Author-email: muti.kara@ug.bilkent.edu.tr
Classifier: Development Status :: 3 - Alpha
Classifier: License :: OSI Approved :: MIT License
Classifier: Programming Language :: Python :: 3.11
License-File: LICENSE
Requires-Dist: pydantic
Requires-Dist: fastapi
Requires-Dist: uvicorn
Requires-Dist: rpyc
